{"html": "<body bgcolor=\"#FFFFFF\">\n\n<p><a href=\"/\">HOME</a> / <a href=\"/press/press.shtml\">PRESS OFFICE</a><br/>\n<br/>\n<a href=\"http://www.fec.gov\">\n<img src=\"../../jpg/topfec.jpg\" border=\"0\" alt=\"FEC Home Page\" width=\"81\" height=\"81\"/></a> </p>\n\n<table border=\"0\" width=\"100%\" cellpadding=\"0\" cellspacing=\"24\">\n  <tr>\n    <th width=\"100%\" class=\"fourteen_pt\"/>\n  </tr>\n  <tr>\n    <td width=\"100%\">\n    <p class=\"MsoNormal\" align=\"center\"><b>\n    <span>Notice</span></b></p>\n    <p class=\"MsoNormal\">\n    <span>The deadline for comments on the Federal \n    Election Commission&#146;s rulemaking on political committees is April 9, 2004.</span></p>\n    <p class=\"MsoNormal\">\n    <span>No comments received after that date will be \n    considered in the rulemaking process.&#160; Comments sent to the email account \n    after that date will be automatically rejected.&#160; Comments received by fax, \n    mail, or hand delivery after that date will be returned.</span></p>\n    <p align=\"CENTER\"># # #</p></td>\n  </tr>\n  <tr>\n    <td width=\"100%\"/>\n  </tr>\n</table>\n</body>\n", "date": "04/07/2004", "href": "press2004/20040407advisory.html", "category": "Rulemakings", "title": "Commission Will Not Accept Late Comments on the Political Committee Status NPRM", "pdf": null}