{"date": "09/05/2014", "pdf": null, "title": "Week of September 1 - September 5, 2014", "issue": "2014-36", "html": "<div id=\"fec_mainContentWide\">\n  <div> \n    <br/>\n    <table width=\"100%\" cellpadding=\"0\" cellspacing=\"0\">\n      <tr>\n        <td colspan=\"2\" valign=\"top\"><strong>For Immediate Release</strong></td>\n        <td width=\"7%\" valign=\"top\"><div align=\"right\"><strong>Contact</strong>: </div></td>\n        <td width=\"16%\" valign=\"top\">Judith Ingram</td>\n      </tr>\n      <tr>\n        <td colspan=\"2\" valign=\"top\">September 5, 2014</td>\n        <td valign=\"top\">&#160;</td>\n        <td valign=\"top\">Christian Hilland</td>\n      </tr>\n      <tr>\n        <td colspan=\"2\" valign=\"top\">&#160;</td>\n        <td valign=\"top\">&#160;</td>\n        <td valign=\"top\">Julia Queen </td>\n      </tr>\n      <tr>\n        <td colspan=\"2\" valign=\"top\">&#160;</td>\n        <td valign=\"top\">&#160;</td>\n        <td valign=\"top\">&#160;</td>\n      </tr>\n      <tr>\n        <td width=\"3%\" valign=\"top\"><div align=\"center\"><img width=\"16\" vspace=\"0\" hspace=\"0\" height=\"16\" align=\"default\" alt=\"PDF\" src=\"../../../images/filetype-pdf.gif\"/> </div></td>\n        <td width=\"74%\" valign=\"top\"><a href=\"../pdf/20140905digest.pdf\">.pdf version of this Weekly Digest </a></td>\n        <td valign=\"top\">&#160;</td>\n        <td valign=\"top\">ISSUE 2014-36</td>\n      </tr>\n      <tr>\n        <td colspan=\"2\" valign=\"top\">&#160;</td>\n        <td valign=\"top\">&#160;</td>\n        <td valign=\"top\">&#160;</td>\n      </tr>\n      <tr>\n        <td colspan=\"4\" valign=\"top\"><p align=\"center\"><strong>Weekly Digest</strong></p>\n          <p align=\"center\"><strong>Week of September 1 &#8211; 5</strong></p>\n          <p><strong/></p>\n          <p><strong>COMMISSION MEETINGS AND HEARINGS</strong></p>\n          <p/>\n          <p>No Commission open meetings or executive sessions were scheduled this week.<br/>\n          </p>\n          <p/>\n          <p><strong>ADVISORY OPINIONS</strong></p>\n          <p><strong/></p>\n          <p><u>Requests Received</u></p>\n          <p><u/></p>\n          <p><a href=\"http://saos.fec.gov/aodocs/1304060.pdf\">AOR 2014-14 (Trammell)</a>. On September 3, 2014, the Commission made public Advisory Opinion Request 2014-14. Professor Jack Trammell is a candidate for the United States House of Representatives, and he asks whether his employer, Randolph-Macon College, may continue to pay its share of his fringe benefits while he is on unpaid leave in order to campaign. Trammell requests expedited consideration of his Advisory Opinion Request pursuant to the Commission's <a href=\"../../../law/cfr/ej_compilation/2009/notice_2009-11.pdf\">Advisory Opinion Procedure</a>. </p>\n          <p/>\n          <p/>\n          <p><a href=\"http://saos.fec.gov/aodocs/1304061.pdf\">AOR 2014-15 (Brat)</a>. On September 3, 2014, the Commission made public Advisory Opinion Request 2014-15. Professor David Brat is a candidate for the United States House of Representatives, and he asks whether his employer, Randolph-Macon College, may continue to pay its share of his fringe benefits while he is on unpaid leave in order to campaign. Brat requests expedited consideration of his Advisory Opinion Request pursuant to the Commission's <a href=\"../../../law/cfr/ej_compilation/2009/notice_2009-11.pdf\">Advisory Opinion Procedure</a> </p>\n          <p/>\n          <p><strong>ADMINISTRATIVE FINES<br/>\n          </strong></p>\n          <p>The Commission made public two campaign finance enforcement matters that were resolved through its Administrative Fines (AF) program, as follows. For more information, see the case documents in the <a href=\"http://eqs.fec.gov/eqs/searcheqs\">Enforcement Query System</a>.</p>\n          <p/>\n          <p><a href=\"http://eqs.fec.gov/eqs/searcheqs\">AF 2636</a>&#8211; Garcia for Congress and Swati Patel, in her official capacity as treasurer. The Commission made a final determination and assessed a civil penalty of $15,220.</p>\n          <p/>\n          <p><a href=\"http://eqs.fec.gov/eqs/searcheqs\">AF 2790</a>&#8211; Texans for Lamar Smith and Pike Powers, in his official capacity as treasurer. The Commission made a final determination and assessed a civil penalty of $2,890.</p>\n          <p/>\n          <p><strong>LITIGATION<br/>\n          </strong></p>\n          <p><a href=\"../../../law/litigation/crew110951_complaint.pdf\"><em>Citizens for Responsibility and Ethics in Washington (CREW) v. FEC</em></a> (No. 11-cv-00951(CKK)). On September 5, the United States District Court for the District of Columbia issued a <a href=\"../../../law/litigation/crew110951_dc_memo_opin_fees.pdf\">Memorandum Opinion</a> and <a href=\"../../../law/litigation/crew110951_dc_order_fees.pdf\">Order</a>, awarding the plaintiff $500 in costs and $153, 258.98 in fees.</p>\n          <p/>\n          <p/>\n          <p><strong>LEGAL DEVELOPMENTS</strong><br/>\n          </p>\n          <p><a href=\"../../../pages/fecrecord/2014/september/fecamovesto52usc.shtml\">FECA Moves from Title 2 to Title 52 of the United States Code</a>. As of September 1, 2014, federal campaign finance laws (currently found in 2 U.S.C. &#167; 431, <em>et seq.</em>) have been consolidated with other laws governing voting and elections in the new title 52 of the United States Code. The FEC will compile and distribute a new version of our <a href=\"../../../law/feca/feca.pdf\">\"Orange Book\"</a> to reflect the changes. </p>\n          <p/>\n          <p><strong>OUTREACH</strong></p>\n          <p/>\n          <p>On September 5-7, Vice Chair Ann M. Ravel attended the California Political Attorneys Association conference and spoke about the work of the Commission.</p>\n          <p/>\n          <p><strong>PRESS RELEASES<br/>\n                <br/>\n            </strong><a href=\"../news_releases/20140905release.shtml\">FEC Cites Committee for Failure to File 12-Day Pre-Primary Financial Report</a> (issued September 5) <strong><br/>\n            <br/>\n  UPCOMING EVENTS</strong></p>\n          <p><a href=\"../news_releases/20140814release_1.shtml\">Public Forum on Website Improvement</a>. The FEC&#8217;s Public Forum on Website Improvement is scheduled for September 17. In partnership with 18F, a newly formed organization within the General Services Administration (GSA), the FEC has launched a website redesign effort to improve the public&#8217;s access to campaign finance data, guidance and regulations, and filing information.&#160; An open discussion with Commissioners and senior staff will be held from 10:00-12:00 pm, and working group breakout sessions with Commission staff moderated by 18F will meet from 1:00-3:00 pm.&#160; Space is limited; if you would like to participate in person, please email us at <a href=\"mailto:websiteforum@fec.gov\">websiteforum@fec.gov</a>.&#160; Alternatively, you may listen to the open discussion through a live audio feed available on FEC.gov, which requires no pre-registration. </p>\n          <p><strong>UPCOMING COMMISSION MEETINGS </strong></p>\n          <p><strong/></p>\n          <p>September 9: The Commission is scheduled to hold an <a href=\"../../../agenda/agendas.shtml#executive\">executive session</a>.</p>\n          <p/>\n          <p>September 11: The previously scheduled open meeting was cancelled.</p>\n          <p/>\n          <p>Meeting dates are subject to change. Please contact the Press Office the week of the scheduled meeting for confirmation.<br/>\n          </p>\n          <p><strong>UPCOMING EDUCATIONAL PROGRAMS</strong></p>\n          <p><strong/></p>\n          <p>October 1, 2014, Federal Election Commission, Washington, DC. <em>Webinar on October Quarterly Reporting for Candidate Committees</em>. Additional information is available on the <a href=\"../../../info/outreach.shtml\">Educational Outreach </a>page of the Commission website.</p>\n          <p/>\n          <p>October 1, 2014, Federal Election Commission, Washington, DC. <em>Webinar on FECFiling for Candidate Committees</em>. Additional information is available on the <a href=\"../../../info/outreach.shtml\">Educational Outreach</a> page of the Commission website.</p>\n          <p/>\n          <p>October 8, 2014, Federal Election Commission, Washington, DC. <em>Webinar and In-Person Workshop on October Reporting for PACs and Party Committees</em>. Additional information is available on the <a href=\"../../../info/outreach.shtml\">Educational Outreach</a> page of the Commission website.</p>\n          <p/>\n          <p>October 8, 2014, Federal Election Commission, Washington, DC. <em>Webinar and In-Person Workshop on</em> <em>FECFiling for PACs and Party Committees</em>. Additional information is available on the <a href=\"../../../info/outreach.shtml\">Educational Outreach</a> page of the Commission website.</p>\n          <p/>\n          <p><strong>UPCOMING REPORTING DUE DATES</strong></p>\n          <p/>\n          <p>September 20: September Monthly Reports are due. For more information on monthly reporting dates, refer to the <a href=\"../../../info/report_dates_2014.shtml#monthly\">2014 Monthly Reporting page</a> of the Commission website.</p>\n          <p/>\n          <p>October 15: Quarterly Reports are due. For information on quarterly reporting dates, refer to the <a href=\"../../../info/report_dates_2014.shtml#quarterly\">2014 Quarterly Reporting page</a> of the Commission website.</p>\n          <p><strong/></p>\n          <p><strong>OTHER RESOURCES </strong></p>\n          <p><strong/></p>\n          <p>The <a href=\"../../../pubrec/cfsdd/cfsdd.shtml\">2014 edition of the Combined Federal State Disclosure and Election Directory</a> is available in the <a href=\"../../../pubrec/publicrecordsoffice.shtml#using\">Public Records</a> section of the Commission website. This publication identifies the federal and state agencies responsible for the disclosure of campaign finances, lobbying, personal finances, public financing, candidates on the ballot, election results, spending on state initiatives and other financial filings.</p>\n          <p/>\n          <p>The 2014 edition of <a href=\"../../../law/cfr/2014cfr.pdf\">Title 11 of the Code of Federal Regulations</a> can be downloaded from the website. &#160;To order printed copies, call (800) 424-9530 (press 6) or send an email to <a href=\"mailto:info@fec.gov?subject=Candidate%20Guide\">info@fec.gov</a>.</p>\n          <p/>\n          <p>The <a href=\"../../../law/legrec2013.pdf\">2013 Legislative Recommendations</a> are available on the Commission&#8217;s website.</p>\n          <p/>\n          <p>The 2014 edition of the <a href=\"../../../pdf/candgui.pdf\">Federal Election Commission Campaign Guide for Congressional Candidates and Committees</a> is now available on the Commission&#8217;s website. </p>\n          <p/>\n          <p>The August 2013 edition of the <a href=\"../../../pdf/partygui.pdf\">Federal Election Commission Campaign Guide for Political Party Committees</a> is available on the Commission&#8217;s website. </p>\n          <p/>\n          <p>The <a href=\"../../../pubrec/fe2012/2012presgeresults.pdf\">Official 2012 Presidential General Election Results</a> are available in the <a href=\"../../../general/library.shtml\">Library</a> section of the website. This listing was compiled from the official election results published by state election offices.</p>\n          <p/>\n          <p>An <a href=\"../../../pages/record.shtml#Y2014\">index</a> to Record news articles published is available on the Commission website. The <a href=\"../../../pages/fecrecord/fecrecord.shtml\">Record</a> news page is available in the <a href=\"../../../pages/record.shtml\">Publications</a> section of the Commission website. <a href=\"../../../pages/record.shtml\">Sign up</a> to receive email notification when new articles are posted. </p>\n          <p/>\n          <p>The <a href=\"../../../pages/anreport.shtml\">FEC Annual Reports from 1975-2006</a> are now available on the website. Beginning in 2007, the Commission consolidated its Annual Report with its <a href=\"../../../pages/budget/budget.shtml#PAR\">Performance and Accountability Report (PAR)</a> to provide a single account of the agency&#8217;s activities for each fiscal year.</p>\n          <p/>\n          <p><a href=\"../../../info/elearning.shtml\">Instructional videos</a> are available on YouTube at http://www.youtube.com/user/FECTube?feature=watch. These videos are also available on the Commission&#8217;s E-Learning resources page at http://www.fec.gov/info/elearning.shtml.</p>\n          <p align=\"center\"/>\n          <p align=\"center\">Follow us on Twitter - <a href=\"http://twitter.com/fec\">http://twitter.com/fec</a></p>\n          <p align=\"center\"/>\n          <p align=\"center\">Users of smartphones and other mobile devices may access our mobile interface at <a href=\"../../../mobile/\">http://www.fec.gov/mobile</a></p>\n          <p align=\"center\">&#160;</p>\n        </td>\n      </tr>\n      <tr>\n        <td colspan=\"2\"/>\n      </tr><tr>\n        <td colspan=\"2\"/>\n      </tr>\n    </table>\n    <div id=\"fec_press_content\">\n      <div class=\"digest_content\"><br/>\n</div>\n    </div>\n  </div>\n</div>\n", "href": "press2014/digests/20140905digest.shtml"}